qlapi_nrsdk/__init__.py
qlapi_nrsdk/base.py
qlapi_nrsdk/mcf_reader.py
qlapi_nrsdk/nrsdk.py
qlapi_nrsdk/paradigm.py
qlapi_nrsdk/rsa.py
qlapi_nrsdk/lib/QLNRSdk.dll
qlapi_nrsdk/neuro_recorder/__init__.py
qlapi_nrsdk-0.1.4.dist-info/METADATA
qlapi_nrsdk-0.1.4.dist-info/WHEEL
qlapi_nrsdk-0.1.4.dist-info/top_level.txt
qlapi_nrsdk-0.1.4.dist-info/RECORD
