Metadata-Version: 2.1
Name: qlapi-nrsdk
Version: 0.1.4
Summary: Api for use quanlan device, since v1.1.1
Author: eegion
Author-email: hehuajun@eegion.com
Requires: beautifulsoup
Requires: lxml
